<Properties StartupConfiguration="{AD1D1674-D3C2-42FA-9A7E-85357E4C792F}|https">
  <MonoDevelop.Ide.DebuggingService.PinnedWatches />
  <MonoDevelop.Ide.ItemProperties.Server PreferredExecutionTarget="/Applications/Google Chrome.app" />
  <MonoDevelop.Ide.Workbench ActiveDocument="TelegramBotListify/Program.cs">
    <Files>
      <File FileName="ServerLibrary/Repositories/Contracts/IUserRepository.cs" Line="14" Column="1" />
      <File FileName="ServerLibrary/Repositories/Implementations/UserRepository.cs" Line="36" Column="10" />
      <File FileName="TelegramBotListify/Program.cs" Line="59" Column="13" />
    </Files>
    <Pads>
      <Pad Id="ProjectPad">
        <State name="__root__">
          <Node name="Listify" expanded="True" selected="True" />
        </State>
      </Pad>
    </Pads>
  </MonoDevelop.Ide.Workbench>
  <MonoDevelop.Ide.Workspace ActiveConfiguration="Debug" />
  <MonoDevelop.Ide.DebuggingService.Breakpoints>
    <BreakpointStore />
  </MonoDevelop.Ide.DebuggingService.Breakpoints>
  <MultiItemStartupConfigurations />
</Properties>